{
  "SaveName": "",
  "Date": "",
  "VersionNumber": "",
  "GameMode": "",
  "GameType": "",
  "GameComplexity": "",
  "Tags": [],
  "Gravity": 0.5,
  "PlayArea": 0.5,
  "Table": "",
  "Sky": "",
  "Note": "",
  "TabStates": {},
  "LuaScript": "",
  "LuaScriptState": "",
  "XmlUI": "",
  "ObjectStates": [
    {
      "GUID": "d19666",
      "Name": "Custom_Assetbundle",
      "Transform": {
        "posX": 11.5686436,
        "posY": 1.01159489,
        "posZ": -68.2096,
        "rotX": 0.142950073,
        "rotY": 259.040344,
        "rotZ": 0.14963156,
        "scaleX": 1.25,
        "scaleY": 1.25,
        "scaleZ": 1.25
      },
      "Nickname": "",
      "Description": "",
      "GMNotes": "",
      "AltLookAngle": {
        "x": 0.0,
        "y": 0.0,
        "z": 0.0
      },
      "ColorDiffuse": {
        "r": 1.0,
        "g": 1.0,
        "b": 1.0
      },
      "LayoutGroupSortIndex": 0,
      "Value": 0,
      "Locked": false,
      "Grid": true,
      "Snap": true,
      "IgnoreFoW": false,
      "MeasureMovement": false,
      "DragSelectable": true,
      "Autoraise": true,
      "Sticky": true,
      "Tooltip": true,
      "GridProjection": false,
      "HideWhenFaceDown": false,
      "Hands": false,
      "CustomAssetbundle": {
        "AssetbundleURL": "http://cloud-3.steamusercontent.com/ugc/1756940555595546746/7251FD34E5BDA86024ACD90C8779AC821CC9ADD8/",
        "AssetbundleSecondaryURL": "",
        "MaterialIndex": 0,
        "TypeIndex": 0,
        "LoopingEffectIndex": 0
      },
      "LuaScript": "",
      "LuaScriptState": "",
      "XmlUI": ""
    }
  ]
}