{
  "SaveName": "",
  "Date": "",
  "VersionNumber": "",
  "GameMode": "",
  "GameType": "",
  "GameComplexity": "",
  "Tags": [],
  "Gravity": 0.5,
  "PlayArea": 0.5,
  "Table": "",
  "Sky": "",
  "Note": "",
  "TabStates": {},
  "LuaScript": "",
  "LuaScriptState": "",
  "XmlUI": "",
  "ObjectStates": [
    {
      "GUID": "8fe584",
      "Name": "Custom_Model",
      "Transform": {
        "posX": -21.5536442,
        "posY": 0.9734939,
        "posZ": 9.6468935,
        "rotX": 0.000128565531,
        "rotY": 89.78245,
        "rotZ": -6.926255E-05,
        "scaleX": 0.250000447,
        "scaleY": 0.250000447,
        "scaleZ": 0.250000447
      },
      "Nickname": "",
      "Description": "",
      "GMNotes": "",
      "AltLookAngle": {
        "x": 0.0,
        "y": 0.0,
        "z": 0.0
      },
      "ColorDiffuse": {
        "r": 1.0,
        "g": 1.0,
        "b": 1.0
      },
      "LayoutGroupSortIndex": 0,
      "Value": 0,
      "Locked": true,
      "Grid": true,
      "Snap": true,
      "IgnoreFoW": false,
      "MeasureMovement": false,
      "DragSelectable": true,
      "Autoraise": true,
      "Sticky": true,
      "Tooltip": true,
      "GridProjection": false,
      "HideWhenFaceDown": false,
      "Hands": false,
      "CustomMesh": {
        "MeshURL": "https://steamusercontent-a.akamaihd.net/ugc/84846159839528621/2CA8CBD55DC3DBCA12AA4BF5D7FAE47C15A5370D/",
        "DiffuseURL": "https://steamusercontent-a.akamaihd.net/ugc/84846159839531426/F42BB02973419C19611D6FE37D0916E584F4DF50/",
        "NormalURL": "",
        "ColliderURL": "https://steamusercontent-a.akamaihd.net/ugc/84846159839528621/2CA8CBD55DC3DBCA12AA4BF5D7FAE47C15A5370D/",
        "Convex": false,
        "MaterialIndex": 3,
        "TypeIndex": 1,
        "CastShadows": true
      },
      "LuaScript": "\nBCBtype = \"terrain\"\n",
      "LuaScriptState": "",
      "XmlUI": ""
    }
  ]
}