{
  "SaveName": "",
  "Date": "",
  "VersionNumber": "",
  "GameMode": "",
  "GameType": "",
  "GameComplexity": "",
  "Tags": [],
  "Gravity": 0.5,
  "PlayArea": 0.5,
  "Table": "",
  "Sky": "",
  "Note": "",
  "TabStates": {},
  "LuaScript": "",
  "LuaScriptState": "",
  "XmlUI": "",
  "ObjectStates": [
    {
      "GUID": "17afe6",
      "Name": "Custom_Model",
      "Transform": {
        "posX": -18.80754,
        "posY": 3.41901875,
        "posZ": 19.300602,
        "rotX": -9.90652552E-06,
        "rotY": 90.01383,
        "rotZ": 4.74391572E-06,
        "scaleX": 1.72251606,
        "scaleY": 1.73858023,
        "scaleZ": 1.306682
      },
      "Nickname": "helm",
      "Description": "",
      "GMNotes": "",
      "AltLookAngle": {
        "x": 0.0,
        "y": 0.0,
        "z": 0.0
      },
      "ColorDiffuse": {
        "r": 1.0,
        "g": 1.0,
        "b": 1.0
      },
      "LayoutGroupSortIndex": 0,
      "Value": 0,
      "Locked": true,
      "Grid": true,
      "Snap": true,
      "IgnoreFoW": false,
      "MeasureMovement": false,
      "DragSelectable": true,
      "Autoraise": true,
      "Sticky": true,
      "Tooltip": true,
      "GridProjection": false,
      "HideWhenFaceDown": false,
      "Hands": false,
      "CustomMesh": {
        "MeshURL": "http://cloud-3.steamusercontent.com/ugc/90478669043253093/4DDCE53078804F387F94B78B614CC931CE91CBE6/",
        "DiffuseURL": "http://cloud-3.steamusercontent.com/ugc/90478669043253351/9689997B5A2096E730804ECDC7391D35F2089407/",
        "NormalURL": "",
        "ColliderURL": "",
        "Convex": true,
        "MaterialIndex": 0,
        "TypeIndex": 1,
        "CustomShader": {
          "SpecularColor": {
            "r": 1.0,
            "g": 1.0,
            "b": 1.0
          },
          "SpecularIntensity": 0.0,
          "SpecularSharpness": 7.0,
          "FresnelStrength": 0.4
        },
        "CastShadows": true
      },
      "LuaScript": "",
      "LuaScriptState": "",
      "XmlUI": ""
    }
  ]
}