{
  "SaveName": "",
  "Date": "",
  "VersionNumber": "",
  "GameMode": "",
  "GameType": "",
  "GameComplexity": "",
  "Tags": [],
  "Gravity": 0.5,
  "PlayArea": 0.5,
  "Table": "",
  "Sky": "",
  "Note": "",
  "TabStates": {},
  "LuaScript": "",
  "LuaScriptState": "",
  "XmlUI": "",
  "ObjectStates": [
    {
      "GUID": "d5cc65",
      "Name": "Custom_Model",
      "Transform": {
        "posX": -4.30666542,
        "posY": 4.121318,
        "posZ": -15.7355518,
        "rotX": -7.47051945E-06,
        "rotY": 270.002625,
        "rotZ": 1.23202753,
        "scaleX": 1.0,
        "scaleY": 1.0,
        "scaleZ": 1.0
      },
      "Nickname": "",
      "Description": "",
      "GMNotes": "",
      "AltLookAngle": {
        "x": 0.0,
        "y": 0.0,
        "z": 0.0
      },
      "ColorDiffuse": {
        "r": 1.0,
        "g": 1.0,
        "b": 1.0
      },
      "LayoutGroupSortIndex": 0,
      "Value": 0,
      "Locked": true,
      "Grid": true,
      "Snap": true,
      "IgnoreFoW": false,
      "MeasureMovement": false,
      "DragSelectable": true,
      "Autoraise": true,
      "Sticky": true,
      "Tooltip": true,
      "GridProjection": false,
      "HideWhenFaceDown": false,
      "Hands": false,
      "CustomMesh": {
        "MeshURL": "http://cloud-3.steamusercontent.com/ugc/2303092842275007041/E6C5A678C3867B29A47FA51B654E1DA92F3C9CE6/",
        "DiffuseURL": "http://cloud-3.steamusercontent.com/ugc/2303092842275145624/7AB3D759A83A1C2B1114C7CC429700D1EDB19308/",
        "NormalURL": "",
        "ColliderURL": "http://cloud-3.steamusercontent.com/ugc/2303092842275007041/E6C5A678C3867B29A47FA51B654E1DA92F3C9CE6/",
        "Convex": false,
        "MaterialIndex": 3,
        "TypeIndex": 0,
        "CustomShader": {
          "SpecularColor": {
            "r": 1.0,
            "g": 1.0,
            "b": 1.0
          },
          "SpecularIntensity": 0.0,
          "SpecularSharpness": 2.0,
          "FresnelStrength": 0.0
        },
        "CastShadows": true
      },
      "LuaScript": "",
      "LuaScriptState": "",
      "XmlUI": "",
      "States": {
        "9": {
          "GUID": "1639c8",
          "Name": "Custom_Model",
          "Transform": {
            "posX": -40.0029678,
            "posY": -0.293010473,
            "posZ": -8.862376,
            "rotX": 0.0009377703,
            "rotY": 90.00015,
            "rotZ": 0.08733254,
            "scaleX": 1.0,
            "scaleY": 1.0,
            "scaleZ": 1.0
          },
          "Nickname": "",
          "Description": "",
          "GMNotes": "",
          "AltLookAngle": {
            "x": 0.0,
            "y": 0.0,
            "z": 0.0
          },
          "ColorDiffuse": {
            "r": 1.0,
            "g": 1.0,
            "b": 1.0
          },
          "LayoutGroupSortIndex": 0,
          "Value": 0,
          "Locked": false,
          "Grid": true,
          "Snap": true,
          "IgnoreFoW": false,
          "MeasureMovement": false,
          "DragSelectable": true,
          "Autoraise": true,
          "Sticky": true,
          "Tooltip": true,
          "GridProjection": false,
          "HideWhenFaceDown": false,
          "Hands": false,
          "CustomMesh": {
            "MeshURL": "http://cloud-3.steamusercontent.com/ugc/2303092842275007041/E6C5A678C3867B29A47FA51B654E1DA92F3C9CE6/",
            "DiffuseURL": "http://cloud-3.steamusercontent.com/ugc/2303092842275221191/99AD7D82D422E8C6EE3C428DA077617C1556A791/",
            "NormalURL": "",
            "ColliderURL": "http://cloud-3.steamusercontent.com/ugc/2303092842275007041/E6C5A678C3867B29A47FA51B654E1DA92F3C9CE6/",
            "Convex": false,
            "MaterialIndex": 3,
            "TypeIndex": 0,
            "CustomShader": {
              "SpecularColor": {
                "r": 1.0,
                "g": 1.0,
                "b": 1.0
              },
              "SpecularIntensity": 0.0,
              "SpecularSharpness": 2.0,
              "FresnelStrength": 0.0
            },
            "CastShadows": true
          },
          "LuaScript": "",
          "LuaScriptState": "",
          "XmlUI": ""
        },
        "8": {
          "GUID": "c3c75e",
          "Name": "Custom_Model",
          "Transform": {
            "posX": -40.0029678,
            "posY": -0.2930113,
            "posZ": -8.862337,
            "rotX": 0.0009357826,
            "rotY": 89.99972,
            "rotZ": 0.08720213,
            "scaleX": 1.0,
            "scaleY": 1.0,
            "scaleZ": 1.0
          },
          "Nickname": "",
          "Description": "",
          "GMNotes": "",
          "AltLookAngle": {
            "x": 0.0,
            "y": 0.0,
            "z": 0.0
          },
          "ColorDiffuse": {
            "r": 1.0,
            "g": 1.0,
            "b": 1.0
          },
          "LayoutGroupSortIndex": 0,
          "Value": 0,
          "Locked": false,
          "Grid": true,
          "Snap": true,
          "IgnoreFoW": false,
          "MeasureMovement": false,
          "DragSelectable": true,
          "Autoraise": true,
          "Sticky": true,
          "Tooltip": true,
          "GridProjection": false,
          "HideWhenFaceDown": false,
          "Hands": false,
          "CustomMesh": {
            "MeshURL": "http://cloud-3.steamusercontent.com/ugc/2303092842275007041/E6C5A678C3867B29A47FA51B654E1DA92F3C9CE6/",
            "DiffuseURL": "http://cloud-3.steamusercontent.com/ugc/2303092842275011014/F2F628B42597532C93AB87E9D068437A01A84E0D/",
            "NormalURL": "",
            "ColliderURL": "http://cloud-3.steamusercontent.com/ugc/2303092842275007041/E6C5A678C3867B29A47FA51B654E1DA92F3C9CE6/",
            "Convex": false,
            "MaterialIndex": 3,
            "TypeIndex": 0,
            "CustomShader": {
              "SpecularColor": {
                "r": 1.0,
                "g": 1.0,
                "b": 1.0
              },
              "SpecularIntensity": 0.0,
              "SpecularSharpness": 2.0,
              "FresnelStrength": 0.0
            },
            "CastShadows": true
          },
          "LuaScript": "",
          "LuaScriptState": "",
          "XmlUI": ""
        },
        "7": {
          "GUID": "891c14",
          "Name": "Custom_Model",
          "Transform": {
            "posX": -40.61719,
            "posY": 0.0163860321,
            "posZ": -10.1730089,
            "rotX": -1.24330791E-05,
            "rotY": 89.99849,
            "rotZ": 359.437378,
            "scaleX": 1.0,
            "scaleY": 1.0,
            "scaleZ": 1.0
          },
          "Nickname": "",
          "Description": "",
          "GMNotes": "",
          "AltLookAngle": {
            "x": 0.0,
            "y": 0.0,
            "z": 0.0
          },
          "ColorDiffuse": {
            "r": 1.0,
            "g": 1.0,
            "b": 1.0
          },
          "LayoutGroupSortIndex": 0,
          "Value": 0,
          "Locked": false,
          "Grid": true,
          "Snap": true,
          "IgnoreFoW": false,
          "MeasureMovement": false,
          "DragSelectable": true,
          "Autoraise": true,
          "Sticky": true,
          "Tooltip": true,
          "GridProjection": false,
          "HideWhenFaceDown": false,
          "Hands": false,
          "CustomMesh": {
            "MeshURL": "http://cloud-3.steamusercontent.com/ugc/2303092842275007041/E6C5A678C3867B29A47FA51B654E1DA92F3C9CE6/",
            "DiffuseURL": "http://cloud-3.steamusercontent.com/ugc/2303092842275134163/A225255C572BE5BE5DDF45CA28C8429A34385E9E/",
            "NormalURL": "",
            "ColliderURL": "http://cloud-3.steamusercontent.com/ugc/2303092842275007041/E6C5A678C3867B29A47FA51B654E1DA92F3C9CE6/",
            "Convex": false,
            "MaterialIndex": 3,
            "TypeIndex": 0,
            "CustomShader": {
              "SpecularColor": {
                "r": 1.0,
                "g": 1.0,
                "b": 1.0
              },
              "SpecularIntensity": 0.0,
              "SpecularSharpness": 2.0,
              "FresnelStrength": 0.0
            },
            "CastShadows": true
          },
          "LuaScript": "",
          "LuaScriptState": "",
          "XmlUI": ""
        },
        "6": {
          "GUID": "33e90c",
          "Name": "Custom_Model",
          "Transform": {
            "posX": -40.4251823,
            "posY": -0.290890217,
            "posZ": -9.342478,
            "rotX": 0.000502659241,
            "rotY": 89.99394,
            "rotZ": 2.22981834,
            "scaleX": 1.0,
            "scaleY": 1.0,
            "scaleZ": 1.0
          },
          "Nickname": "",
          "Description": "",
          "GMNotes": "",
          "AltLookAngle": {
            "x": 0.0,
            "y": 0.0,
            "z": 0.0
          },
          "ColorDiffuse": {
            "r": 1.0,
            "g": 1.0,
            "b": 1.0
          },
          "LayoutGroupSortIndex": 0,
          "Value": 0,
          "Locked": false,
          "Grid": true,
          "Snap": true,
          "IgnoreFoW": false,
          "MeasureMovement": false,
          "DragSelectable": true,
          "Autoraise": true,
          "Sticky": true,
          "Tooltip": true,
          "GridProjection": false,
          "HideWhenFaceDown": false,
          "Hands": false,
          "CustomMesh": {
            "MeshURL": "http://cloud-3.steamusercontent.com/ugc/2303092842275007041/E6C5A678C3867B29A47FA51B654E1DA92F3C9CE6/",
            "DiffuseURL": "http://cloud-3.steamusercontent.com/ugc/2303092842275141380/C2C061B265773E0F60CA8CAEE3771B4925F01F1E/",
            "NormalURL": "",
            "ColliderURL": "http://cloud-3.steamusercontent.com/ugc/2303092842275007041/E6C5A678C3867B29A47FA51B654E1DA92F3C9CE6/",
            "Convex": false,
            "MaterialIndex": 3,
            "TypeIndex": 0,
            "CustomShader": {
              "SpecularColor": {
                "r": 1.0,
                "g": 1.0,
                "b": 1.0
              },
              "SpecularIntensity": 0.0,
              "SpecularSharpness": 2.0,
              "FresnelStrength": 0.0
            },
            "CastShadows": true
          },
          "LuaScript": "",
          "LuaScriptState": "",
          "XmlUI": ""
        },
        "5": {
          "GUID": "9ddf78",
          "Name": "Custom_Model",
          "Transform": {
            "posX": -40.42518,
            "posY": -0.291397929,
            "posZ": -9.258616,
            "rotX": 2.5132962E-05,
            "rotY": 89.99569,
            "rotZ": 358.3938,
            "scaleX": 1.0,
            "scaleY": 1.0,
            "scaleZ": 1.0
          },
          "Nickname": "",
          "Description": "",
          "GMNotes": "",
          "AltLookAngle": {
            "x": 0.0,
            "y": 0.0,
            "z": 0.0
          },
          "ColorDiffuse": {
            "r": 1.0,
            "g": 1.0,
            "b": 1.0
          },
          "LayoutGroupSortIndex": 0,
          "Value": 0,
          "Locked": false,
          "Grid": true,
          "Snap": true,
          "IgnoreFoW": false,
          "MeasureMovement": false,
          "DragSelectable": true,
          "Autoraise": true,
          "Sticky": true,
          "Tooltip": true,
          "GridProjection": false,
          "HideWhenFaceDown": false,
          "Hands": false,
          "CustomMesh": {
            "MeshURL": "http://cloud-3.steamusercontent.com/ugc/2303092842275007041/E6C5A678C3867B29A47FA51B654E1DA92F3C9CE6/",
            "DiffuseURL": "http://cloud-3.steamusercontent.com/ugc/2303092842275211830/8A22703AF5C4A1334C904A35E4D6BDF9023CC401/",
            "NormalURL": "",
            "ColliderURL": "http://cloud-3.steamusercontent.com/ugc/2303092842275007041/E6C5A678C3867B29A47FA51B654E1DA92F3C9CE6/",
            "Convex": false,
            "MaterialIndex": 3,
            "TypeIndex": 0,
            "CustomShader": {
              "SpecularColor": {
                "r": 1.0,
                "g": 1.0,
                "b": 1.0
              },
              "SpecularIntensity": 0.0,
              "SpecularSharpness": 2.0,
              "FresnelStrength": 0.0
            },
            "CastShadows": true
          },
          "LuaScript": "",
          "LuaScriptState": "",
          "XmlUI": ""
        },
        "4": {
          "GUID": "76fe3b",
          "Name": "Custom_Model",
          "Transform": {
            "posX": -40.3124733,
            "posY": -0.289819479,
            "posZ": -9.104875,
            "rotX": 359.992859,
            "rotY": 89.99506,
            "rotZ": 2.84765577,
            "scaleX": 1.0,
            "scaleY": 1.0,
            "scaleZ": 1.0
          },
          "Nickname": "",
          "Description": "",
          "GMNotes": "",
          "AltLookAngle": {
            "x": 0.0,
            "y": 0.0,
            "z": 0.0
          },
          "ColorDiffuse": {
            "r": 1.0,
            "g": 1.0,
            "b": 1.0
          },
          "LayoutGroupSortIndex": 0,
          "Value": 0,
          "Locked": false,
          "Grid": true,
          "Snap": true,
          "IgnoreFoW": false,
          "MeasureMovement": false,
          "DragSelectable": true,
          "Autoraise": true,
          "Sticky": true,
          "Tooltip": true,
          "GridProjection": false,
          "HideWhenFaceDown": false,
          "Hands": false,
          "CustomMesh": {
            "MeshURL": "http://cloud-3.steamusercontent.com/ugc/2303092842275007041/E6C5A678C3867B29A47FA51B654E1DA92F3C9CE6/",
            "DiffuseURL": "http://cloud-3.steamusercontent.com/ugc/2303092842275148485/875E3205821D956458C59902F246FEEF324FA161/",
            "NormalURL": "",
            "ColliderURL": "http://cloud-3.steamusercontent.com/ugc/2303092842275007041/E6C5A678C3867B29A47FA51B654E1DA92F3C9CE6/",
            "Convex": false,
            "MaterialIndex": 3,
            "TypeIndex": 0,
            "CustomShader": {
              "SpecularColor": {
                "r": 1.0,
                "g": 1.0,
                "b": 1.0
              },
              "SpecularIntensity": 0.0,
              "SpecularSharpness": 2.0,
              "FresnelStrength": 0.0
            },
            "CastShadows": true
          },
          "LuaScript": "",
          "LuaScriptState": "",
          "XmlUI": ""
        },
        "1": {
          "GUID": "f9c5ba",
          "Name": "Custom_Model",
          "Transform": {
            "posX": -10.9402294,
            "posY": 3.87367725,
            "posZ": -11.3298349,
            "rotX": -6.625727E-05,
            "rotY": 180.005554,
            "rotZ": 179.738678,
            "scaleX": 1.0,
            "scaleY": 1.0,
            "scaleZ": 1.0
          },
          "Nickname": "",
          "Description": "",
          "GMNotes": "",
          "AltLookAngle": {
            "x": 0.0,
            "y": 0.0,
            "z": 0.0
          },
          "ColorDiffuse": {
            "r": 1.0,
            "g": 1.0,
            "b": 1.0
          },
          "LayoutGroupSortIndex": 0,
          "Value": 0,
          "Locked": false,
          "Grid": true,
          "Snap": true,
          "IgnoreFoW": false,
          "MeasureMovement": false,
          "DragSelectable": true,
          "Autoraise": true,
          "Sticky": true,
          "Tooltip": true,
          "GridProjection": false,
          "HideWhenFaceDown": false,
          "Hands": false,
          "CustomMesh": {
            "MeshURL": "http://cloud-3.steamusercontent.com/ugc/2303092842275007041/E6C5A678C3867B29A47FA51B654E1DA92F3C9CE6/",
            "DiffuseURL": "http://cloud-3.steamusercontent.com/ugc/2303092842275007800/B702B47D218218F1F5BB9D44D1235B38165F34E5/",
            "NormalURL": "",
            "ColliderURL": "http://cloud-3.steamusercontent.com/ugc/2303092842275007041/E6C5A678C3867B29A47FA51B654E1DA92F3C9CE6/",
            "Convex": false,
            "MaterialIndex": 3,
            "TypeIndex": 0,
            "CustomShader": {
              "SpecularColor": {
                "r": 1.0,
                "g": 1.0,
                "b": 1.0
              },
              "SpecularIntensity": 0.0,
              "SpecularSharpness": 2.0,
              "FresnelStrength": 0.0
            },
            "CastShadows": true
          },
          "LuaScript": "",
          "LuaScriptState": "",
          "XmlUI": ""
        },
        "2": {
          "GUID": "92c3f1",
          "Name": "Custom_Model",
          "Transform": {
            "posX": -8.304107,
            "posY": -0.192187309,
            "posZ": -10.4139624,
            "rotX": 0.000140679578,
            "rotY": 0.005551325,
            "rotZ": 359.052673,
            "scaleX": 1.0,
            "scaleY": 1.0,
            "scaleZ": 1.0
          },
          "Nickname": "",
          "Description": "",
          "GMNotes": "",
          "AltLookAngle": {
            "x": 0.0,
            "y": 0.0,
            "z": 0.0
          },
          "ColorDiffuse": {
            "r": 1.0,
            "g": 1.0,
            "b": 1.0
          },
          "LayoutGroupSortIndex": 0,
          "Value": 0,
          "Locked": false,
          "Grid": true,
          "Snap": true,
          "IgnoreFoW": false,
          "MeasureMovement": false,
          "DragSelectable": true,
          "Autoraise": true,
          "Sticky": true,
          "Tooltip": true,
          "GridProjection": false,
          "HideWhenFaceDown": false,
          "Hands": false,
          "CustomMesh": {
            "MeshURL": "http://cloud-3.steamusercontent.com/ugc/2303092842275007041/E6C5A678C3867B29A47FA51B654E1DA92F3C9CE6/",
            "DiffuseURL": "http://cloud-3.steamusercontent.com/ugc/2303092842275219589/759AF679A3EA53C0450FB55FD354E1F95C176AEA/",
            "NormalURL": "",
            "ColliderURL": "http://cloud-3.steamusercontent.com/ugc/2303092842275007041/E6C5A678C3867B29A47FA51B654E1DA92F3C9CE6/",
            "Convex": false,
            "MaterialIndex": 3,
            "TypeIndex": 0,
            "CustomShader": {
              "SpecularColor": {
                "r": 1.0,
                "g": 1.0,
                "b": 1.0
              },
              "SpecularIntensity": 0.0,
              "SpecularSharpness": 2.0,
              "FresnelStrength": 0.0
            },
            "CastShadows": true
          },
          "LuaScript": "",
          "LuaScriptState": "",
          "XmlUI": ""
        }
      }
    }
  ]
}